LICENSE
README.md
setup.py
json_xwininfo/__init__.py
json_xwininfo/main.py
json_xwininfo.egg-info/PKG-INFO
json_xwininfo.egg-info/SOURCES.txt
json_xwininfo.egg-info/dependency_links.txt
json_xwininfo.egg-info/entry_points.txt
json_xwininfo.egg-info/requires.txt
json_xwininfo.egg-info/top_level.txt