Metadata-Version: 2.1
Name: json-xwininfo
Version: 1.0.0
Summary: Various convenience functions to get json information similar to xwininfo
Home-page: https://github.com/talwrii/json-xwininfo
Author: @readwithai
Author-email: talwrii@gmail.com
License: BSD with added link requirement
License-File: LICENSE
